sphinx_pytest/__init__.py
sphinx_pytest/builders.py
sphinx_pytest/plugin.py
sphinx_pytest-0.3.0.dist-info/entry_points.txt
sphinx_pytest-0.3.0.dist-info/licenses/LICENSE
sphinx_pytest-0.3.0.dist-info/WHEEL
sphinx_pytest-0.3.0.dist-info/METADATA
sphinx_pytest-0.3.0.dist-info/RECORD
