Metadata-Version: 2.4
Name: sphinx_pytest
Version: 0.3.0
Summary: Helpful pytest fixtures for sphinx extensions.
Keywords: sphinx,pytest
Author-email: Chris Sewell <chrisj_sewell@hotmail.com>
Requires-Python: >=3.10
Classifier: License :: OSI Approved :: MIT License
Classifier: Programming Language :: Python :: 3
Classifier: Programming Language :: Python :: 3.10
Classifier: Programming Language :: Python :: 3.11
Classifier: Programming Language :: Python :: 3.12
Classifier: Programming Language :: Python :: 3.13
Classifier: Programming Language :: Python :: Implementation :: CPython
Classifier: Topic :: Software Development :: Libraries :: Python Modules
Classifier: Framework :: Pytest
License-File: LICENSE
Requires-Dist: sphinx
Requires-Dist: pytest
Project-URL: Homepage, https://github.com/sphinx-extensions2/sphinx-pytest
